raydbg/__init__.py
raydbg/cli.py
raydbg/codeql.py
raydbg/dynamic_analysis.py
raydbg/executor.py
raydbg/llm.py
raydbg/utils.py
raydbg/queries/codeql-pack.lock.yml
raydbg/queries/qlpack.yml
raydbg/queries/queries.xml
raydbg/queries/ray_define_in_loop.ql
raydbg/queries/ray_global_var1.ql
raydbg/queries/ray_global_var2.ql
raydbg/queries/unnecessary_ray_get.ql
raydbg-0.1.0.dist-info/METADATA
raydbg-0.1.0.dist-info/WHEEL
raydbg-0.1.0.dist-info/entry_points.txt
raydbg-0.1.0.dist-info/top_level.txt
raydbg-0.1.0.dist-info/RECORD
