Metadata-Version: 2.1
Name: raydbg
Version: 0.1.0
Summary: A tool for debugging Ray programs
Home-page: https://github.com/shouc/raydbg
Author: Chaofan Shou
Author-email: shou@berkeley.edu
Classifier: Programming Language :: Python :: 3
Classifier: License :: OSI Approved :: MIT License
Classifier: Operating System :: OS Independent
Requires-Python: >=3.6
Requires-Dist: wget (==3.2)
Requires-Dist: retry (==0.9.2)
Requires-Dist: openai (==0.28.0)
Requires-Dist: ray
